{



    "blog": {
        "builder": true,
        "name": "Blog Section",
        "content": {
            "heading": "text",
            "sub_heading": "text"
        },
        "element": {
            "images": {
                "image": {
                    "size": "965x450",
                    "thumb": "415x305"
                }
            },
            "title": "text",
            "description": "textarea-nic",
            "modal": false
        }
    },



    "contact": {
        "builder": true,
        "no_selection": true,
        "name": "Contact Section",
        "content": {
            "heading": "text",
            "sub_heading": "text",
            "map": "text"
        },
        "element": {
            "icon": "icon",
            "title": "text",
            "content": "text",
            "modal": true
        }
    }

}
